datacache/__init__.py
datacache/cache.py
datacache/common.py
datacache/database.py
datacache/database_helpers.py
datacache/database_table.py
datacache/database_types.py
datacache/download.py
datacache/version.py
datacache-1.4.1.dist-info/LICENSE
datacache-1.4.1.dist-info/METADATA
datacache-1.4.1.dist-info/WHEEL
datacache-1.4.1.dist-info/top_level.txt
datacache-1.4.1.dist-info/RECORD
