Metadata-Version: 2.1
Name: datacache
Version: 1.4.1
Summary: Helpers for transparently downloading datasets
Home-page: https://github.com/openvax/datacache
Author: Alex Rubinsteyn
Author-email: alex.rubinsteyn@unc.edu
License: http://www.apache.org/licenses/LICENSE-2.0.html
Classifier: Development Status :: 4 - Beta
Classifier: Environment :: Console
Classifier: Operating System :: OS Independent
Classifier: Intended Audience :: Science/Research
Classifier: License :: OSI Approved :: Apache Software License
Classifier: Programming Language :: Python
Classifier: Topic :: Scientific/Engineering :: Bio-Informatics
License-File: LICENSE
Requires-Dist: pandas >=0.15.2
Requires-Dist: appdirs >=1.4.0
Requires-Dist: progressbar33 >=2.4
Requires-Dist: requests >=2.5.1
Requires-Dist: typechecks >=0.0.2
Requires-Dist: mock
